reset/reset.v
module reset #(parameter COUNT = 8) (
    input wire clk,
    input wire en,
    output wire reset
);

reg [COUNT-1:0] counter = {COUNT{1'b1}};

always @ (posedge clk)
begin
    counter <= {1'b1, counter[COUNT-1:1]};
    if (en)
    begin
        counter <= {COUNT{1'b0}};
    end
end

assign reset = counter[0];

endmodule

reset/reset_tb.v
`timescale 1ns/1ps
module reset_tb;

reg clk;
reg en;

wire rst_out;

reset rst(clk, en, rst_out);

always
    #10 clk = ~clk;

initial
begin
    clk = 0;
    en = 0;
    @(posedge clk);
    en = 1;
    @(posedge clk);
    en = 0;
end

initial
begin
    #400 $finish;
end

initial
begin
    $dumpfile("reset_tb.vcd");
    $dumpvars(0, reset_tb);
end

endmodule

reset/reset_tb.vcd
$date
	Fri Sep  2 22:35:57 2016
$end
$version
	Icarus Verilog
$end
$timescale
	1ps
$end
$scope module reset_tb $end
$var wire 1 ! rst_out $end
$var reg 1 " clk $end
$var reg 1 # en $end
$scope module rst $end
$var wire 1 $ clk $end
$var wire 1 % en $end
$var wire 1 ! reset $end
$var reg 8 & counter [7:0] $end
$upscope $end
$upscope $end
$enddefinitions $end
#0
$dumpvars
b11111111 &
0%
0$
0#
0"
1!
$end
#10000
0!
b0 &
1#
1%
1"
1$
#20000
0"
0$
#30000
b0 &
0#
0%
1"
1$
#40000
0"
0$
#50000
b10000000 &
1"
1$
#60000
0"
0$
#70000
b11000000 &
1"
1$
#80000
0"
0$
#90000
b11100000 &
1"
1$
#100000
0"
0$
#110000
b11110000 &
1"
1$
#120000
0"
0$
#130000
b11111000 &
1"
1$
#140000
0"
0$
#150000
b11111100 &
1"
1$
#160000
0"
0$
#170000
b11111110 &
1"
1$
#180000
0"
0$
#190000
1!
b11111111 &
1"
1$
